LICENSE.rst
MANIFEST.in
README.rst
setup.py
openrange/__init__.py
openrange/base.py
openrange/dt.py
openrange/rng.py
openrange.egg-info/PKG-INFO
openrange.egg-info/SOURCES.txt
openrange.egg-info/dependency_links.txt
openrange.egg-info/requires.txt
openrange.egg-info/top_level.txt
openrange/tests/__init__.py
openrange/tests/test_BaseRange.py
openrange/tests/test_DateRange.py
openrange/tests/test_DatetimeRange.py
openrange/tests/test_Range.py
openrange/tests/test_TimeRange.py
openrange/tests/test_range.py