Metadata-Version: 1.1
Name: openrange
Version: 1.1.0
Summary: OpenRange provides a simple interface for building custom arithmetic progression objects. Quickly create range-like generators for any objects that can be represented numerically.
Home-page: https://github.com/josh-t/openrange
Author: Josh Tomlinson
Author-email: joshetomlinson@gmail.com
License: MIT
Keywords: openrange range interval progression
Platform: UNKNOWN
Classifier: Development Status :: 2 - Pre-Alpha
Classifier: Intended Audience :: Developers
Classifier: License :: OSI Approved :: MIT License
Classifier: Natural Language :: English
Classifier: Operating System :: OS Independent
Classifier: Programming Language :: Python
Classifier: Programming Language :: Python :: 2
Classifier: Programming Language :: Python :: 2.7
Classifier: Topic :: Software Development :: Libraries :: Python Modules
